spectrabuster/__init__.py
spectrabuster/Saver/__init__.py
spectrabuster/Saver/saver.py
spectrabuster/Saver/specsaver.py
spectrabuster/Spectrum/__init__.py
spectrabuster/Spectrum/spectrum.py
spectrabuster/backends/__init__.py
spectrabuster/backends/cseabreeze.py
spectrabuster/backends/none.py
spectrabuster/backends/pyseabreeze.py
spectrabuster/backends/seatease.py
spectrabuster/functions/__init__.py
spectrabuster/functions/backend_functions.py
spectrabuster-0.2.dist-info/LICENSE
spectrabuster-0.2.dist-info/METADATA
spectrabuster-0.2.dist-info/WHEEL
spectrabuster-0.2.dist-info/top_level.txt
spectrabuster-0.2.dist-info/RECORD
