Metadata-Version: 2.1
Name: spectrabuster
Version: 0.2
Summary: Tools for simplifying the handling of spectrums acquired using python-seabreeze
Home-page: https://github.com/eduardosprp/spectrabuster
Author: Eduardo Lopes Dias
Author-email: eduardotogpi@usp.br
License: UNKNOWN
Project-URL: Bug Tracker, https://github.com/eduardosprp/spectrabuster/issues
Platform: UNKNOWN
Classifier: Programming Language :: Python :: 3
Classifier: License :: OSI Approved :: MIT License
Classifier: Operating System :: OS Independent
Requires-Python: >=3.6
License-File: LICENSE
Requires-Dist: scipy
Requires-Dist: matplotlib
Provides-Extra: measurements
Requires-Dist: seabreeze ; extra == 'measurements'
Provides-Extra: seabreeze_emulation
Requires-Dist: seatease ; extra == 'seabreeze_emulation'
